[
  {
    "login":"kovacshuni",
    "id":1782646,
    "avatar_url":"https://avatars3.githubusercontent.com/u/1782646?v=4",
    "gravatar_id":"",
    "url":"https://api.github.com/users/kovacshuni",
    "html_url":"https://github.com/kovacshuni",
    "followers_url":"https://api.github.com/users/kovacshuni/followers",
    "following_url":"https://api.github.com/users/kovacshuni/following{/other_user}",
    "gists_url":"https://api.github.com/users/kovacshuni/gists{/gist_id}",
    "starred_url":"https://api.github.com/users/kovacshuni/starred{/owner}{/repo}",
    "subscriptions_url":"https://api.github.com/users/kovacshuni/subscriptions",
    "organizations_url":"https://api.github.com/users/kovacshuni/orgs",
    "repos_url":"https://api.github.com/users/kovacshuni/repos",
    "events_url":"https://api.github.com/users/kovacshuni/events{/privacy}",
    "received_events_url":"https://api.github.com/users/kovacshuni/received_events",
    "type":"User",
    "site_admin":false,
    "contributions":148
  }
]