[
  {
    "login":"holograph",
    "id":1114848,
    "avatar_url":"https://avatars.githubusercontent.com/u/1114848?v=3",
    "gravatar_id":"",
    "url":"https://api.github.com/users/holograph",
    "html_url":"https://github.com/holograph",
    "followers_url":"https://api.github.com/users/holograph/followers",
    "following_url":"https://api.github.com/users/holograph/following{/other_user}",
    "gists_url":"https://api.github.com/users/holograph/gists{/gist_id}",
    "starred_url":"https://api.github.com/users/holograph/starred{/owner}{/repo}",
    "subscriptions_url":"https://api.github.com/users/holograph/subscriptions",
    "organizations_url":"https://api.github.com/users/holograph/orgs",
    "repos_url":"https://api.github.com/users/holograph/repos",
    "events_url":"https://api.github.com/users/holograph/events{/privacy}",
    "received_events_url":"https://api.github.com/users/holograph/received_events",
    "type":"User",
    "site_admin":false,
    "contributions":442
  },
  {
    "login":"xeno-by",
    "id":609152,
    "avatar_url":"https://avatars.githubusercontent.com/u/609152?v=3",
    "gravatar_id":"",
    "url":"https://api.github.com/users/xeno-by",
    "html_url":"https://github.com/xeno-by",
    "followers_url":"https://api.github.com/users/xeno-by/followers",
    "following_url":"https://api.github.com/users/xeno-by/following{/other_user}",
    "gists_url":"https://api.github.com/users/xeno-by/gists{/gist_id}",
    "starred_url":"https://api.github.com/users/xeno-by/starred{/owner}{/repo}",
    "subscriptions_url":"https://api.github.com/users/xeno-by/subscriptions",
    "organizations_url":"https://api.github.com/users/xeno-by/orgs",
    "repos_url":"https://api.github.com/users/xeno-by/repos",
    "events_url":"https://api.github.com/users/xeno-by/events{/privacy}",
    "received_events_url":"https://api.github.com/users/xeno-by/received_events",
    "type":"User",
    "site_admin":false,
    "contributions":5
  },
  {
    "login":"yaronyam",
    "id":10505445,
    "avatar_url":"https://avatars.githubusercontent.com/u/10505445?v=3",
    "gravatar_id":"",
    "url":"https://api.github.com/users/yaronyam",
    "html_url":"https://github.com/yaronyam",
    "followers_url":"https://api.github.com/users/yaronyam/followers",
    "following_url":"https://api.github.com/users/yaronyam/following{/other_user}",
    "gists_url":"https://api.github.com/users/yaronyam/gists{/gist_id}",
    "starred_url":"https://api.github.com/users/yaronyam/starred{/owner}{/repo}",
    "subscriptions_url":"https://api.github.com/users/yaronyam/subscriptions",
    "organizations_url":"https://api.github.com/users/yaronyam/orgs",
    "repos_url":"https://api.github.com/users/yaronyam/repos",
    "events_url":"https://api.github.com/users/yaronyam/events{/privacy}",
    "received_events_url":"https://api.github.com/users/yaronyam/received_events",
    "type":"User",
    "site_admin":false,
    "contributions":1
  },
  {
    "login":"nadavwe",
    "id":10103990,
    "avatar_url":"https://avatars.githubusercontent.com/u/10103990?v=3",
    "gravatar_id":"",
    "url":"https://api.github.com/users/nadavwe",
    "html_url":"https://github.com/nadavwe",
    "followers_url":"https://api.github.com/users/nadavwe/followers",
    "following_url":"https://api.github.com/users/nadavwe/following{/other_user}",
    "gists_url":"https://api.github.com/users/nadavwe/gists{/gist_id}",
    "starred_url":"https://api.github.com/users/nadavwe/starred{/owner}{/repo}",
    "subscriptions_url":"https://api.github.com/users/nadavwe/subscriptions",
    "organizations_url":"https://api.github.com/users/nadavwe/orgs",
    "repos_url":"https://api.github.com/users/nadavwe/repos",
    "events_url":"https://api.github.com/users/nadavwe/events{/privacy}",
    "received_events_url":"https://api.github.com/users/nadavwe/received_events",
    "type":"User",
    "site_admin":false,
    "contributions":1
  }
]