{
  "health_percentage":33,
  "description":"Tiny type generator for scala ",
  "documentation":null,
  "files":{
    "code_of_conduct":null,
    "contributing":null,
    "issue_template":null,
    "pull_request_template":null,
    "license":{
      "key":"mit",
      "name":"MIT License",
      "spdx_id":"MIT",
      "url":"https://api.github.com/licenses/mit",
      "html_url":"https://github.com/paradoxical-io/scala-tiny-types/blob/master/LICENSE"
    },
    "readme":{
      "url":"https://api.github.com/repos/paradoxical-io/scala-tiny-types/contents/README.md",
      "html_url":"https://github.com/paradoxical-io/scala-tiny-types/blob/master/README.md"
    }
  },
  "updated_at":"2016-11-08T19:59:57Z"
}