[
  {
    "login":"Mygod",
    "id":3511321,
    "avatar_url":"https://avatars2.githubusercontent.com/u/3511321?v=3",
    "gravatar_id":"",
    "url":"https://api.github.com/users/Mygod",
    "html_url":"https://github.com/Mygod",
    "followers_url":"https://api.github.com/users/Mygod/followers",
    "following_url":"https://api.github.com/users/Mygod/following{/other_user}",
    "gists_url":"https://api.github.com/users/Mygod/gists{/gist_id}",
    "starred_url":"https://api.github.com/users/Mygod/starred{/owner}{/repo}",
    "subscriptions_url":"https://api.github.com/users/Mygod/subscriptions",
    "organizations_url":"https://api.github.com/users/Mygod/orgs",
    "repos_url":"https://api.github.com/users/Mygod/repos",
    "events_url":"https://api.github.com/users/Mygod/events{/privacy}",
    "received_events_url":"https://api.github.com/users/Mygod/received_events",
    "type":"User",
    "site_admin":false,
    "contributions":260
  }
]