[
  {
    "login":"nicf82",
    "id":1664536,
    "avatar_url":"https://avatars1.githubusercontent.com/u/1664536?v=4",
    "gravatar_id":"",
    "url":"https://api.github.com/users/nicf82",
    "html_url":"https://github.com/nicf82",
    "followers_url":"https://api.github.com/users/nicf82/followers",
    "following_url":"https://api.github.com/users/nicf82/following{/other_user}",
    "gists_url":"https://api.github.com/users/nicf82/gists{/gist_id}",
    "starred_url":"https://api.github.com/users/nicf82/starred{/owner}{/repo}",
    "subscriptions_url":"https://api.github.com/users/nicf82/subscriptions",
    "organizations_url":"https://api.github.com/users/nicf82/orgs",
    "repos_url":"https://api.github.com/users/nicf82/repos",
    "events_url":"https://api.github.com/users/nicf82/events{/privacy}",
    "received_events_url":"https://api.github.com/users/nicf82/received_events",
    "type":"User",
    "site_admin":false,
    "contributions":47
  },
  {
    "login":"richardjamesbaconHMRC",
    "id":29404321,
    "avatar_url":"https://avatars0.githubusercontent.com/u/29404321?v=4",
    "gravatar_id":"",
    "url":"https://api.github.com/users/richardjamesbaconHMRC",
    "html_url":"https://github.com/richardjamesbaconHMRC",
    "followers_url":"https://api.github.com/users/richardjamesbaconHMRC/followers",
    "following_url":"https://api.github.com/users/richardjamesbaconHMRC/following{/other_user}",
    "gists_url":"https://api.github.com/users/richardjamesbaconHMRC/gists{/gist_id}",
    "starred_url":"https://api.github.com/users/richardjamesbaconHMRC/starred{/owner}{/repo}",
    "subscriptions_url":"https://api.github.com/users/richardjamesbaconHMRC/subscriptions",
    "organizations_url":"https://api.github.com/users/richardjamesbaconHMRC/orgs",
    "repos_url":"https://api.github.com/users/richardjamesbaconHMRC/repos",
    "events_url":"https://api.github.com/users/richardjamesbaconHMRC/events{/privacy}",
    "received_events_url":"https://api.github.com/users/richardjamesbaconHMRC/received_events",
    "type":"User",
    "site_admin":false,
    "contributions":22
  },
  {
    "login":"gianick",
    "id":8497852,
    "avatar_url":"https://avatars2.githubusercontent.com/u/8497852?v=4",
    "gravatar_id":"",
    "url":"https://api.github.com/users/gianick",
    "html_url":"https://github.com/gianick",
    "followers_url":"https://api.github.com/users/gianick/followers",
    "following_url":"https://api.github.com/users/gianick/following{/other_user}",
    "gists_url":"https://api.github.com/users/gianick/gists{/gist_id}",
    "starred_url":"https://api.github.com/users/gianick/starred{/owner}{/repo}",
    "subscriptions_url":"https://api.github.com/users/gianick/subscriptions",
    "organizations_url":"https://api.github.com/users/gianick/orgs",
    "repos_url":"https://api.github.com/users/gianick/repos",
    "events_url":"https://api.github.com/users/gianick/events{/privacy}",
    "received_events_url":"https://api.github.com/users/gianick/received_events",
    "type":"User",
    "site_admin":false,
    "contributions":15
  },
  {
    "login":"derek-gray",
    "id":29451372,
    "avatar_url":"https://avatars0.githubusercontent.com/u/29451372?v=4",
    "gravatar_id":"",
    "url":"https://api.github.com/users/derek-gray",
    "html_url":"https://github.com/derek-gray",
    "followers_url":"https://api.github.com/users/derek-gray/followers",
    "following_url":"https://api.github.com/users/derek-gray/following{/other_user}",
    "gists_url":"https://api.github.com/users/derek-gray/gists{/gist_id}",
    "starred_url":"https://api.github.com/users/derek-gray/starred{/owner}{/repo}",
    "subscriptions_url":"https://api.github.com/users/derek-gray/subscriptions",
    "organizations_url":"https://api.github.com/users/derek-gray/orgs",
    "repos_url":"https://api.github.com/users/derek-gray/repos",
    "events_url":"https://api.github.com/users/derek-gray/events{/privacy}",
    "received_events_url":"https://api.github.com/users/derek-gray/received_events",
    "type":"User",
    "site_admin":false,
    "contributions":14
  },
  {
    "login":"hmrc-web-operations",
    "id":6948709,
    "avatar_url":"https://avatars0.githubusercontent.com/u/6948709?v=4",
    "gravatar_id":"",
    "url":"https://api.github.com/users/hmrc-web-operations",
    "html_url":"https://github.com/hmrc-web-operations",
    "followers_url":"https://api.github.com/users/hmrc-web-operations/followers",
    "following_url":"https://api.github.com/users/hmrc-web-operations/following{/other_user}",
    "gists_url":"https://api.github.com/users/hmrc-web-operations/gists{/gist_id}",
    "starred_url":"https://api.github.com/users/hmrc-web-operations/starred{/owner}{/repo}",
    "subscriptions_url":"https://api.github.com/users/hmrc-web-operations/subscriptions",
    "organizations_url":"https://api.github.com/users/hmrc-web-operations/orgs",
    "repos_url":"https://api.github.com/users/hmrc-web-operations/repos",
    "events_url":"https://api.github.com/users/hmrc-web-operations/events{/privacy}",
    "received_events_url":"https://api.github.com/users/hmrc-web-operations/received_events",
    "type":"User",
    "site_admin":false,
    "contributions":4
  },
  {
    "login":"thoeni",
    "id":2122700,
    "avatar_url":"https://avatars1.githubusercontent.com/u/2122700?v=4",
    "gravatar_id":"",
    "url":"https://api.github.com/users/thoeni",
    "html_url":"https://github.com/thoeni",
    "followers_url":"https://api.github.com/users/thoeni/followers",
    "following_url":"https://api.github.com/users/thoeni/following{/other_user}",
    "gists_url":"https://api.github.com/users/thoeni/gists{/gist_id}",
    "starred_url":"https://api.github.com/users/thoeni/starred{/owner}{/repo}",
    "subscriptions_url":"https://api.github.com/users/thoeni/subscriptions",
    "organizations_url":"https://api.github.com/users/thoeni/orgs",
    "repos_url":"https://api.github.com/users/thoeni/repos",
    "events_url":"https://api.github.com/users/thoeni/events{/privacy}",
    "received_events_url":"https://api.github.com/users/thoeni/received_events",
    "type":"User",
    "site_admin":false,
    "contributions":1
  },
  {
    "login":"ChrisTennant123",
    "id":21358316,
    "avatar_url":"https://avatars2.githubusercontent.com/u/21358316?v=4",
    "gravatar_id":"",
    "url":"https://api.github.com/users/ChrisTennant123",
    "html_url":"https://github.com/ChrisTennant123",
    "followers_url":"https://api.github.com/users/ChrisTennant123/followers",
    "following_url":"https://api.github.com/users/ChrisTennant123/following{/other_user}",
    "gists_url":"https://api.github.com/users/ChrisTennant123/gists{/gist_id}",
    "starred_url":"https://api.github.com/users/ChrisTennant123/starred{/owner}{/repo}",
    "subscriptions_url":"https://api.github.com/users/ChrisTennant123/subscriptions",
    "organizations_url":"https://api.github.com/users/ChrisTennant123/orgs",
    "repos_url":"https://api.github.com/users/ChrisTennant123/repos",
    "events_url":"https://api.github.com/users/ChrisTennant123/events{/privacy}",
    "received_events_url":"https://api.github.com/users/ChrisTennant123/received_events",
    "type":"User",
    "site_admin":false,
    "contributions":1
  },
  {
    "login":"stjasink",
    "id":8123071,
    "avatar_url":"https://avatars1.githubusercontent.com/u/8123071?v=4",
    "gravatar_id":"",
    "url":"https://api.github.com/users/stjasink",
    "html_url":"https://github.com/stjasink",
    "followers_url":"https://api.github.com/users/stjasink/followers",
    "following_url":"https://api.github.com/users/stjasink/following{/other_user}",
    "gists_url":"https://api.github.com/users/stjasink/gists{/gist_id}",
    "starred_url":"https://api.github.com/users/stjasink/starred{/owner}{/repo}",
    "subscriptions_url":"https://api.github.com/users/stjasink/subscriptions",
    "organizations_url":"https://api.github.com/users/stjasink/orgs",
    "repos_url":"https://api.github.com/users/stjasink/repos",
    "events_url":"https://api.github.com/users/stjasink/events{/privacy}",
    "received_events_url":"https://api.github.com/users/stjasink/received_events",
    "type":"User",
    "site_admin":false,
    "contributions":1
  }
]