[
  {
    "login":"asynchorswim",
    "id":9018986,
    "avatar_url":"https://avatars2.githubusercontent.com/u/9018986?v=4",
    "gravatar_id":"",
    "url":"https://api.github.com/users/asynchorswim",
    "html_url":"https://github.com/asynchorswim",
    "followers_url":"https://api.github.com/users/asynchorswim/followers",
    "following_url":"https://api.github.com/users/asynchorswim/following{/other_user}",
    "gists_url":"https://api.github.com/users/asynchorswim/gists{/gist_id}",
    "starred_url":"https://api.github.com/users/asynchorswim/starred{/owner}{/repo}",
    "subscriptions_url":"https://api.github.com/users/asynchorswim/subscriptions",
    "organizations_url":"https://api.github.com/users/asynchorswim/orgs",
    "repos_url":"https://api.github.com/users/asynchorswim/repos",
    "events_url":"https://api.github.com/users/asynchorswim/events{/privacy}",
    "received_events_url":"https://api.github.com/users/asynchorswim/received_events",
    "type":"User",
    "site_admin":false,
    "contributions":71
  }
]