{
  "data":{
    "repository":{
      "repositoryTopics":{
        "nodes":[
          {
            "topic":{
              "name":"tensei-data"
            }
          },
          {
            "topic":{
              "name":"data-integration"
            }
          },
          {
            "topic":{
              "name":"data-migration"
            }
          },
          {
            "topic":{
              "name":"data-management"
            }
          }
        ]
      }
    }
  }
}