{
  "health_percentage":50,
  "description":"non-official extension library for akka-stream that contains operations like zipWithIndex, Source.fromTry and so on",
  "documentation":null,
  "files":{
    "code_of_conduct":null,
    "contributing":null,
    "issue_template":null,
    "pull_request_template":null,
    "license":{
      "key":"apache-2.0",
      "name":"Apache License 2.0",
      "spdx_id":"Apache-2.0",
      "url":"https://api.github.com/licenses/apache-2.0",
      "html_url":"https://github.com/dnvriend/akka-stream-extensions/blob/master/LICENSE"
    },
    "readme":{
      "url":"https://api.github.com/repos/dnvriend/akka-stream-extensions/contents/README.md",
      "html_url":"https://github.com/dnvriend/akka-stream-extensions/blob/master/README.md"
    }
  },
  "updated_at":"2017-09-12T08:16:22Z"
}