[
  {
    "login":"giabao",
    "id":1702709,
    "avatar_url":"https://avatars0.githubusercontent.com/u/1702709?v=4",
    "gravatar_id":"",
    "url":"https://api.github.com/users/giabao",
    "html_url":"https://github.com/giabao",
    "followers_url":"https://api.github.com/users/giabao/followers",
    "following_url":"https://api.github.com/users/giabao/following{/other_user}",
    "gists_url":"https://api.github.com/users/giabao/gists{/gist_id}",
    "starred_url":"https://api.github.com/users/giabao/starred{/owner}{/repo}",
    "subscriptions_url":"https://api.github.com/users/giabao/subscriptions",
    "organizations_url":"https://api.github.com/users/giabao/orgs",
    "repos_url":"https://api.github.com/users/giabao/repos",
    "events_url":"https://api.github.com/users/giabao/events{/privacy}",
    "received_events_url":"https://api.github.com/users/giabao/received_events",
    "type":"User",
    "site_admin":false,
    "contributions":22
  },
  {
    "login":"ashawley",
    "id":358615,
    "avatar_url":"https://avatars1.githubusercontent.com/u/358615?v=4",
    "gravatar_id":"",
    "url":"https://api.github.com/users/ashawley",
    "html_url":"https://github.com/ashawley",
    "followers_url":"https://api.github.com/users/ashawley/followers",
    "following_url":"https://api.github.com/users/ashawley/following{/other_user}",
    "gists_url":"https://api.github.com/users/ashawley/gists{/gist_id}",
    "starred_url":"https://api.github.com/users/ashawley/starred{/owner}{/repo}",
    "subscriptions_url":"https://api.github.com/users/ashawley/subscriptions",
    "organizations_url":"https://api.github.com/users/ashawley/orgs",
    "repos_url":"https://api.github.com/users/ashawley/repos",
    "events_url":"https://api.github.com/users/ashawley/events{/privacy}",
    "received_events_url":"https://api.github.com/users/ashawley/received_events",
    "type":"User",
    "site_admin":false,
    "contributions":4
  },
  {
    "login":"KhArtNJava",
    "id":757085,
    "avatar_url":"https://avatars1.githubusercontent.com/u/757085?v=4",
    "gravatar_id":"",
    "url":"https://api.github.com/users/KhArtNJava",
    "html_url":"https://github.com/KhArtNJava",
    "followers_url":"https://api.github.com/users/KhArtNJava/followers",
    "following_url":"https://api.github.com/users/KhArtNJava/following{/other_user}",
    "gists_url":"https://api.github.com/users/KhArtNJava/gists{/gist_id}",
    "starred_url":"https://api.github.com/users/KhArtNJava/starred{/owner}{/repo}",
    "subscriptions_url":"https://api.github.com/users/KhArtNJava/subscriptions",
    "organizations_url":"https://api.github.com/users/KhArtNJava/orgs",
    "repos_url":"https://api.github.com/users/KhArtNJava/repos",
    "events_url":"https://api.github.com/users/KhArtNJava/events{/privacy}",
    "received_events_url":"https://api.github.com/users/KhArtNJava/received_events",
    "type":"User",
    "site_admin":false,
    "contributions":3
  }
]