{
  "health_percentage":33,
  "description":"Network storage and analytics library",
  "documentation":"http://teapot-co.github.io/tempest/",
  "files":{
    "code_of_conduct":null,
    "contributing":null,
    "issue_template":null,
    "pull_request_template":null,
    "license":{
      "key":"other",
      "name":"Other",
      "spdx_id":null,
      "url":null,
      "html_url":"https://github.com/teapot-co/tempest/blob/master/LICENSE"
    },
    "readme":{
      "url":"https://api.github.com/repos/teapot-co/tempest/contents/README.md",
      "html_url":"https://github.com/teapot-co/tempest/blob/master/README.md"
    }
  },
  "updated_at":"2017-05-21T18:14:29Z"
}