{
  "health_percentage":25,
  "files":{
    "code_of_conduct":{
      "name":"None",
      "key":"none",
      "url":null,
      "html_url":null
    },
    "contributing":{
      "url":null,
      "html_url":null
    },
    "license":{
      "name":null,
      "key":null,
      "url":null,
      "html_url":null
    },
    "readme":{
      "url":"https://api.github.com/repos/sdb/play2-metrics/contents/README.md",
      "html_url":"https://github.com/sdb/play2-metrics/blob/master/README.md"
    }
  },
  "updated_at":"2017-07-12T16:02:01Z"
}