{
  "id":13205992,
  "name":"DSL-OCD",
  "full_name":"dsl-platform/DSL-OCD",
  "owner":{
    "login":"dsl-platform",
    "id":8957088,
    "avatar_url":"https://avatars1.githubusercontent.com/u/8957088?v=3",
    "gravatar_id":"",
    "url":"https://api.github.com/users/dsl-platform",
    "html_url":"https://github.com/dsl-platform",
    "followers_url":"https://api.github.com/users/dsl-platform/followers",
    "following_url":"https://api.github.com/users/dsl-platform/following{/other_user}",
    "gists_url":"https://api.github.com/users/dsl-platform/gists{/gist_id}",
    "starred_url":"https://api.github.com/users/dsl-platform/starred{/owner}{/repo}",
    "subscriptions_url":"https://api.github.com/users/dsl-platform/subscriptions",
    "organizations_url":"https://api.github.com/users/dsl-platform/orgs",
    "repos_url":"https://api.github.com/users/dsl-platform/repos",
    "events_url":"https://api.github.com/users/dsl-platform/events{/privacy}",
    "received_events_url":"https://api.github.com/users/dsl-platform/received_events",
    "type":"Organization",
    "site_admin":false
  },
  "private":false,
  "html_url":"https://github.com/dsl-platform/DSL-OCD",
  "description":"DSL Platform - Obsesive-Compulsive Testing",
  "fork":false,
  "url":"https://api.github.com/repos/dsl-platform/DSL-OCD",
  "forks_url":"https://api.github.com/repos/dsl-platform/DSL-OCD/forks",
  "keys_url":"https://api.github.com/repos/dsl-platform/DSL-OCD/keys{/key_id}",
  "collaborators_url":"https://api.github.com/repos/dsl-platform/DSL-OCD/collaborators{/collaborator}",
  "teams_url":"https://api.github.com/repos/dsl-platform/DSL-OCD/teams",
  "hooks_url":"https://api.github.com/repos/dsl-platform/DSL-OCD/hooks",
  "issue_events_url":"https://api.github.com/repos/dsl-platform/DSL-OCD/issues/events{/number}",
  "events_url":"https://api.github.com/repos/dsl-platform/DSL-OCD/events",
  "assignees_url":"https://api.github.com/repos/dsl-platform/DSL-OCD/assignees{/user}",
  "branches_url":"https://api.github.com/repos/dsl-platform/DSL-OCD/branches{/branch}",
  "tags_url":"https://api.github.com/repos/dsl-platform/DSL-OCD/tags",
  "blobs_url":"https://api.github.com/repos/dsl-platform/DSL-OCD/git/blobs{/sha}",
  "git_tags_url":"https://api.github.com/repos/dsl-platform/DSL-OCD/git/tags{/sha}",
  "git_refs_url":"https://api.github.com/repos/dsl-platform/DSL-OCD/git/refs{/sha}",
  "trees_url":"https://api.github.com/repos/dsl-platform/DSL-OCD/git/trees{/sha}",
  "statuses_url":"https://api.github.com/repos/dsl-platform/DSL-OCD/statuses/{sha}",
  "languages_url":"https://api.github.com/repos/dsl-platform/DSL-OCD/languages",
  "stargazers_url":"https://api.github.com/repos/dsl-platform/DSL-OCD/stargazers",
  "contributors_url":"https://api.github.com/repos/dsl-platform/DSL-OCD/contributors",
  "subscribers_url":"https://api.github.com/repos/dsl-platform/DSL-OCD/subscribers",
  "subscription_url":"https://api.github.com/repos/dsl-platform/DSL-OCD/subscription",
  "commits_url":"https://api.github.com/repos/dsl-platform/DSL-OCD/commits{/sha}",
  "git_commits_url":"https://api.github.com/repos/dsl-platform/DSL-OCD/git/commits{/sha}",
  "comments_url":"https://api.github.com/repos/dsl-platform/DSL-OCD/comments{/number}",
  "issue_comment_url":"https://api.github.com/repos/dsl-platform/DSL-OCD/issues/comments{/number}",
  "contents_url":"https://api.github.com/repos/dsl-platform/DSL-OCD/contents/{+path}",
  "compare_url":"https://api.github.com/repos/dsl-platform/DSL-OCD/compare/{base}...{head}",
  "merges_url":"https://api.github.com/repos/dsl-platform/DSL-OCD/merges",
  "archive_url":"https://api.github.com/repos/dsl-platform/DSL-OCD/{archive_format}{/ref}",
  "downloads_url":"https://api.github.com/repos/dsl-platform/DSL-OCD/downloads",
  "issues_url":"https://api.github.com/repos/dsl-platform/DSL-OCD/issues{/number}",
  "pulls_url":"https://api.github.com/repos/dsl-platform/DSL-OCD/pulls{/number}",
  "milestones_url":"https://api.github.com/repos/dsl-platform/DSL-OCD/milestones{/number}",
  "notifications_url":"https://api.github.com/repos/dsl-platform/DSL-OCD/notifications{?since,all,participating}",
  "labels_url":"https://api.github.com/repos/dsl-platform/DSL-OCD/labels{/name}",
  "releases_url":"https://api.github.com/repos/dsl-platform/DSL-OCD/releases{/id}",
  "deployments_url":"https://api.github.com/repos/dsl-platform/DSL-OCD/deployments",
  "created_at":"2013-09-30T04:20:11Z",
  "updated_at":"2016-11-24T13:22:52Z",
  "pushed_at":"2017-05-21T08:52:50Z",
  "git_url":"git://github.com/dsl-platform/DSL-OCD.git",
  "ssh_url":"git@github.com:dsl-platform/DSL-OCD.git",
  "clone_url":"https://github.com/dsl-platform/DSL-OCD.git",
  "svn_url":"https://github.com/dsl-platform/DSL-OCD",
  "homepage":"",
  "size":6745,
  "stargazers_count":0,
  "watchers_count":0,
  "language":"Scala",
  "has_issues":true,
  "has_projects":true,
  "has_downloads":true,
  "has_wiki":true,
  "has_pages":false,
  "forks_count":1,
  "mirror_url":null,
  "open_issues_count":0,
  "forks":1,
  "open_issues":0,
  "watchers":0,
  "default_branch":"master",
  "permissions":{
    "admin":false,
    "push":false,
    "pull":true
  },
  "organization":{
    "login":"dsl-platform",
    "id":8957088,
    "avatar_url":"https://avatars1.githubusercontent.com/u/8957088?v=3",
    "gravatar_id":"",
    "url":"https://api.github.com/users/dsl-platform",
    "html_url":"https://github.com/dsl-platform",
    "followers_url":"https://api.github.com/users/dsl-platform/followers",
    "following_url":"https://api.github.com/users/dsl-platform/following{/other_user}",
    "gists_url":"https://api.github.com/users/dsl-platform/gists{/gist_id}",
    "starred_url":"https://api.github.com/users/dsl-platform/starred{/owner}{/repo}",
    "subscriptions_url":"https://api.github.com/users/dsl-platform/subscriptions",
    "organizations_url":"https://api.github.com/users/dsl-platform/orgs",
    "repos_url":"https://api.github.com/users/dsl-platform/repos",
    "events_url":"https://api.github.com/users/dsl-platform/events{/privacy}",
    "received_events_url":"https://api.github.com/users/dsl-platform/received_events",
    "type":"Organization",
    "site_admin":false
  },
  "network_count":1,
  "subscribers_count":9
}