{
  "id":34955679,
  "name":"Neo4S",
  "full_name":"mrkaspa/Neo4S",
  "owner":{
    "login":"mrkaspa",
    "id":764271,
    "avatar_url":"https://avatars0.githubusercontent.com/u/764271?v=3",
    "gravatar_id":"",
    "url":"https://api.github.com/users/mrkaspa",
    "html_url":"https://github.com/mrkaspa",
    "followers_url":"https://api.github.com/users/mrkaspa/followers",
    "following_url":"https://api.github.com/users/mrkaspa/following{/other_user}",
    "gists_url":"https://api.github.com/users/mrkaspa/gists{/gist_id}",
    "starred_url":"https://api.github.com/users/mrkaspa/starred{/owner}{/repo}",
    "subscriptions_url":"https://api.github.com/users/mrkaspa/subscriptions",
    "organizations_url":"https://api.github.com/users/mrkaspa/orgs",
    "repos_url":"https://api.github.com/users/mrkaspa/repos",
    "events_url":"https://api.github.com/users/mrkaspa/events{/privacy}",
    "received_events_url":"https://api.github.com/users/mrkaspa/received_events",
    "type":"User",
    "site_admin":false
  },
  "private":false,
  "html_url":"https://github.com/mrkaspa/Neo4S",
  "description":"Go to the new repository https://github.com/hackersguildco/neo4s",
  "fork":false,
  "url":"https://api.github.com/repos/mrkaspa/Neo4S",
  "forks_url":"https://api.github.com/repos/mrkaspa/Neo4S/forks",
  "keys_url":"https://api.github.com/repos/mrkaspa/Neo4S/keys{/key_id}",
  "collaborators_url":"https://api.github.com/repos/mrkaspa/Neo4S/collaborators{/collaborator}",
  "teams_url":"https://api.github.com/repos/mrkaspa/Neo4S/teams",
  "hooks_url":"https://api.github.com/repos/mrkaspa/Neo4S/hooks",
  "issue_events_url":"https://api.github.com/repos/mrkaspa/Neo4S/issues/events{/number}",
  "events_url":"https://api.github.com/repos/mrkaspa/Neo4S/events",
  "assignees_url":"https://api.github.com/repos/mrkaspa/Neo4S/assignees{/user}",
  "branches_url":"https://api.github.com/repos/mrkaspa/Neo4S/branches{/branch}",
  "tags_url":"https://api.github.com/repos/mrkaspa/Neo4S/tags",
  "blobs_url":"https://api.github.com/repos/mrkaspa/Neo4S/git/blobs{/sha}",
  "git_tags_url":"https://api.github.com/repos/mrkaspa/Neo4S/git/tags{/sha}",
  "git_refs_url":"https://api.github.com/repos/mrkaspa/Neo4S/git/refs{/sha}",
  "trees_url":"https://api.github.com/repos/mrkaspa/Neo4S/git/trees{/sha}",
  "statuses_url":"https://api.github.com/repos/mrkaspa/Neo4S/statuses/{sha}",
  "languages_url":"https://api.github.com/repos/mrkaspa/Neo4S/languages",
  "stargazers_url":"https://api.github.com/repos/mrkaspa/Neo4S/stargazers",
  "contributors_url":"https://api.github.com/repos/mrkaspa/Neo4S/contributors",
  "subscribers_url":"https://api.github.com/repos/mrkaspa/Neo4S/subscribers",
  "subscription_url":"https://api.github.com/repos/mrkaspa/Neo4S/subscription",
  "commits_url":"https://api.github.com/repos/mrkaspa/Neo4S/commits{/sha}",
  "git_commits_url":"https://api.github.com/repos/mrkaspa/Neo4S/git/commits{/sha}",
  "comments_url":"https://api.github.com/repos/mrkaspa/Neo4S/comments{/number}",
  "issue_comment_url":"https://api.github.com/repos/mrkaspa/Neo4S/issues/comments{/number}",
  "contents_url":"https://api.github.com/repos/mrkaspa/Neo4S/contents/{+path}",
  "compare_url":"https://api.github.com/repos/mrkaspa/Neo4S/compare/{base}...{head}",
  "merges_url":"https://api.github.com/repos/mrkaspa/Neo4S/merges",
  "archive_url":"https://api.github.com/repos/mrkaspa/Neo4S/{archive_format}{/ref}",
  "downloads_url":"https://api.github.com/repos/mrkaspa/Neo4S/downloads",
  "issues_url":"https://api.github.com/repos/mrkaspa/Neo4S/issues{/number}",
  "pulls_url":"https://api.github.com/repos/mrkaspa/Neo4S/pulls{/number}",
  "milestones_url":"https://api.github.com/repos/mrkaspa/Neo4S/milestones{/number}",
  "notifications_url":"https://api.github.com/repos/mrkaspa/Neo4S/notifications{?since,all,participating}",
  "labels_url":"https://api.github.com/repos/mrkaspa/Neo4S/labels{/name}",
  "releases_url":"https://api.github.com/repos/mrkaspa/Neo4S/releases{/id}",
  "deployments_url":"https://api.github.com/repos/mrkaspa/Neo4S/deployments",
  "created_at":"2015-05-02T16:51:09Z",
  "updated_at":"2016-02-24T16:22:09Z",
  "pushed_at":"2016-01-13T17:23:38Z",
  "git_url":"git://github.com/mrkaspa/Neo4S.git",
  "ssh_url":"git@github.com:mrkaspa/Neo4S.git",
  "clone_url":"https://github.com/mrkaspa/Neo4S.git",
  "svn_url":"https://github.com/mrkaspa/Neo4S",
  "homepage":"",
  "size":1090,
  "stargazers_count":17,
  "watchers_count":17,
  "language":"Scala",
  "has_issues":true,
  "has_downloads":true,
  "has_wiki":true,
  "has_pages":false,
  "forks_count":2,
  "mirror_url":null,
  "open_issues_count":0,
  "forks":2,
  "open_issues":0,
  "watchers":17,
  "default_branch":"master",
  "permissions":{
    "admin":false,
    "push":false,
    "pull":true
  },
  "network_count":2,
  "subscribers_count":7
}