{
  "health_percentage":50,
  "description":"Telegram Bot API Wrapper for Scala",
  "documentation":null,
  "files":{
    "code_of_conduct":null,
    "contributing":null,
    "issue_template":null,
    "pull_request_template":null,
    "license":{
      "key":"apache-2.0",
      "name":"Apache License 2.0",
      "spdx_id":"Apache-2.0",
      "url":"https://api.github.com/licenses/apache-2.0",
      "html_url":"https://github.com/mukel/telegrambot4s/blob/master/LICENSE"
    },
    "readme":{
      "url":"https://api.github.com/repos/mukel/telegrambot4s/contents/README.md",
      "html_url":"https://github.com/mukel/telegrambot4s/blob/master/README.md"
    }
  },
  "updated_at":"2017-09-23T21:43:51Z"
}