[
  {
    "login":"mslinn",
    "id":485818,
    "avatar_url":"https://avatars2.githubusercontent.com/u/485818?v=4",
    "gravatar_id":"",
    "url":"https://api.github.com/users/mslinn",
    "html_url":"https://github.com/mslinn",
    "followers_url":"https://api.github.com/users/mslinn/followers",
    "following_url":"https://api.github.com/users/mslinn/following{/other_user}",
    "gists_url":"https://api.github.com/users/mslinn/gists{/gist_id}",
    "starred_url":"https://api.github.com/users/mslinn/starred{/owner}{/repo}",
    "subscriptions_url":"https://api.github.com/users/mslinn/subscriptions",
    "organizations_url":"https://api.github.com/users/mslinn/orgs",
    "repos_url":"https://api.github.com/users/mslinn/repos",
    "events_url":"https://api.github.com/users/mslinn/events{/privacy}",
    "received_events_url":"https://api.github.com/users/mslinn/received_events",
    "type":"User",
    "site_admin":false,
    "contributions":37
  }
]