[
  {
    "login":"dlouwers",
    "id":143664,
    "avatar_url":"https://avatars.githubusercontent.com/u/143664?v=3",
    "gravatar_id":"",
    "url":"https://api.github.com/users/dlouwers",
    "html_url":"https://github.com/dlouwers",
    "followers_url":"https://api.github.com/users/dlouwers/followers",
    "following_url":"https://api.github.com/users/dlouwers/following{/other_user}",
    "gists_url":"https://api.github.com/users/dlouwers/gists{/gist_id}",
    "starred_url":"https://api.github.com/users/dlouwers/starred{/owner}{/repo}",
    "subscriptions_url":"https://api.github.com/users/dlouwers/subscriptions",
    "organizations_url":"https://api.github.com/users/dlouwers/orgs",
    "repos_url":"https://api.github.com/users/dlouwers/repos",
    "events_url":"https://api.github.com/users/dlouwers/events{/privacy}",
    "received_events_url":"https://api.github.com/users/dlouwers/received_events",
    "type":"User",
    "site_admin":false,
    "contributions":144
  },
  {
    "login":"mrooding",
    "id":5998869,
    "avatar_url":"https://avatars.githubusercontent.com/u/5998869?v=3",
    "gravatar_id":"",
    "url":"https://api.github.com/users/mrooding",
    "html_url":"https://github.com/mrooding",
    "followers_url":"https://api.github.com/users/mrooding/followers",
    "following_url":"https://api.github.com/users/mrooding/following{/other_user}",
    "gists_url":"https://api.github.com/users/mrooding/gists{/gist_id}",
    "starred_url":"https://api.github.com/users/mrooding/starred{/owner}{/repo}",
    "subscriptions_url":"https://api.github.com/users/mrooding/subscriptions",
    "organizations_url":"https://api.github.com/users/mrooding/orgs",
    "repos_url":"https://api.github.com/users/mrooding/repos",
    "events_url":"https://api.github.com/users/mrooding/events{/privacy}",
    "received_events_url":"https://api.github.com/users/mrooding/received_events",
    "type":"User",
    "site_admin":false,
    "contributions":13
  }
]