{
  "id":26135855,
  "name":"datastore",
  "full_name":"allenai/datastore",
  "owner":{
    "login":"allenai",
    "id":5667695,
    "avatar_url":"https://avatars0.githubusercontent.com/u/5667695?v=3",
    "gravatar_id":"",
    "url":"https://api.github.com/users/allenai",
    "html_url":"https://github.com/allenai",
    "followers_url":"https://api.github.com/users/allenai/followers",
    "following_url":"https://api.github.com/users/allenai/following{/other_user}",
    "gists_url":"https://api.github.com/users/allenai/gists{/gist_id}",
    "starred_url":"https://api.github.com/users/allenai/starred{/owner}{/repo}",
    "subscriptions_url":"https://api.github.com/users/allenai/subscriptions",
    "organizations_url":"https://api.github.com/users/allenai/orgs",
    "repos_url":"https://api.github.com/users/allenai/repos",
    "events_url":"https://api.github.com/users/allenai/events{/privacy}",
    "received_events_url":"https://api.github.com/users/allenai/received_events",
    "type":"Organization",
    "site_admin":false
  },
  "private":false,
  "html_url":"https://github.com/allenai/datastore",
  "description":"Store for immutable objects in S3",
  "fork":false,
  "url":"https://api.github.com/repos/allenai/datastore",
  "forks_url":"https://api.github.com/repos/allenai/datastore/forks",
  "keys_url":"https://api.github.com/repos/allenai/datastore/keys{/key_id}",
  "collaborators_url":"https://api.github.com/repos/allenai/datastore/collaborators{/collaborator}",
  "teams_url":"https://api.github.com/repos/allenai/datastore/teams",
  "hooks_url":"https://api.github.com/repos/allenai/datastore/hooks",
  "issue_events_url":"https://api.github.com/repos/allenai/datastore/issues/events{/number}",
  "events_url":"https://api.github.com/repos/allenai/datastore/events",
  "assignees_url":"https://api.github.com/repos/allenai/datastore/assignees{/user}",
  "branches_url":"https://api.github.com/repos/allenai/datastore/branches{/branch}",
  "tags_url":"https://api.github.com/repos/allenai/datastore/tags",
  "blobs_url":"https://api.github.com/repos/allenai/datastore/git/blobs{/sha}",
  "git_tags_url":"https://api.github.com/repos/allenai/datastore/git/tags{/sha}",
  "git_refs_url":"https://api.github.com/repos/allenai/datastore/git/refs{/sha}",
  "trees_url":"https://api.github.com/repos/allenai/datastore/git/trees{/sha}",
  "statuses_url":"https://api.github.com/repos/allenai/datastore/statuses/{sha}",
  "languages_url":"https://api.github.com/repos/allenai/datastore/languages",
  "stargazers_url":"https://api.github.com/repos/allenai/datastore/stargazers",
  "contributors_url":"https://api.github.com/repos/allenai/datastore/contributors",
  "subscribers_url":"https://api.github.com/repos/allenai/datastore/subscribers",
  "subscription_url":"https://api.github.com/repos/allenai/datastore/subscription",
  "commits_url":"https://api.github.com/repos/allenai/datastore/commits{/sha}",
  "git_commits_url":"https://api.github.com/repos/allenai/datastore/git/commits{/sha}",
  "comments_url":"https://api.github.com/repos/allenai/datastore/comments{/number}",
  "issue_comment_url":"https://api.github.com/repos/allenai/datastore/issues/comments{/number}",
  "contents_url":"https://api.github.com/repos/allenai/datastore/contents/{+path}",
  "compare_url":"https://api.github.com/repos/allenai/datastore/compare/{base}...{head}",
  "merges_url":"https://api.github.com/repos/allenai/datastore/merges",
  "archive_url":"https://api.github.com/repos/allenai/datastore/{archive_format}{/ref}",
  "downloads_url":"https://api.github.com/repos/allenai/datastore/downloads",
  "issues_url":"https://api.github.com/repos/allenai/datastore/issues{/number}",
  "pulls_url":"https://api.github.com/repos/allenai/datastore/pulls{/number}",
  "milestones_url":"https://api.github.com/repos/allenai/datastore/milestones{/number}",
  "notifications_url":"https://api.github.com/repos/allenai/datastore/notifications{?since,all,participating}",
  "labels_url":"https://api.github.com/repos/allenai/datastore/labels{/name}",
  "releases_url":"https://api.github.com/repos/allenai/datastore/releases{/id}",
  "deployments_url":"https://api.github.com/repos/allenai/datastore/deployments",
  "created_at":"2014-11-03T19:53:04Z",
  "updated_at":"2017-01-04T21:47:31Z",
  "pushed_at":"2017-01-04T21:48:39Z",
  "git_url":"git://github.com/allenai/datastore.git",
  "ssh_url":"git@github.com:allenai/datastore.git",
  "clone_url":"https://github.com/allenai/datastore.git",
  "svn_url":"https://github.com/allenai/datastore",
  "homepage":"",
  "size":23010,
  "stargazers_count":2,
  "watchers_count":2,
  "language":"Scala",
  "has_issues":true,
  "has_projects":true,
  "has_downloads":true,
  "has_wiki":true,
  "has_pages":false,
  "forks_count":6,
  "mirror_url":null,
  "open_issues_count":7,
  "forks":6,
  "open_issues":7,
  "watchers":2,
  "default_branch":"master",
  "permissions":{
    "admin":false,
    "push":false,
    "pull":true
  },
  "organization":{
    "login":"allenai",
    "id":5667695,
    "avatar_url":"https://avatars0.githubusercontent.com/u/5667695?v=3",
    "gravatar_id":"",
    "url":"https://api.github.com/users/allenai",
    "html_url":"https://github.com/allenai",
    "followers_url":"https://api.github.com/users/allenai/followers",
    "following_url":"https://api.github.com/users/allenai/following{/other_user}",
    "gists_url":"https://api.github.com/users/allenai/gists{/gist_id}",
    "starred_url":"https://api.github.com/users/allenai/starred{/owner}{/repo}",
    "subscriptions_url":"https://api.github.com/users/allenai/subscriptions",
    "organizations_url":"https://api.github.com/users/allenai/orgs",
    "repos_url":"https://api.github.com/users/allenai/repos",
    "events_url":"https://api.github.com/users/allenai/events{/privacy}",
    "received_events_url":"https://api.github.com/users/allenai/received_events",
    "type":"Organization",
    "site_admin":false
  },
  "network_count":6,
  "subscribers_count":25
}